AUTHORS.rst
HISTORY.rst
LICENSE
MANIFEST.in
README.rst
setup.py
pyuploadcare_sqlalchemy/__init__.py
pyuploadcare_sqlalchemy/types.py
pyuploadcare_sqlalchemy.egg-info/PKG-INFO
pyuploadcare_sqlalchemy.egg-info/SOURCES.txt
pyuploadcare_sqlalchemy.egg-info/dependency_links.txt
pyuploadcare_sqlalchemy.egg-info/requires.txt
pyuploadcare_sqlalchemy.egg-info/top_level.txt