Metadata-Version: 1.1
Name: pyuploadcare-sqlalchemy
Version: 0.5
Summary: Custom fields types for SqlAlchemy which integrated with Uploadcare service.
Home-page: https://github.com/uploadcare/pyuploadcare-sqlalchemy
Author: Uploadcare LLC
Author-email: hello@uploadcare.com
License: MIT
Keywords: pyuploadcare sqlalchemy
Platform: UNKNOWN
Classifier: Development Status :: 4 - Beta
Classifier: Intended Audience :: Developers
Classifier: License :: OSI Approved :: MIT License
Classifier: Natural Language :: English
Classifier: Programming Language :: Python :: 2
Classifier: Programming Language :: Python :: 2.6
Classifier: Programming Language :: Python :: 2.7
Classifier: Programming Language :: Python :: 3
Classifier: Programming Language :: Python :: 3.2
Classifier: Programming Language :: Python :: 3.3
Classifier: Programming Language :: Python :: 3.4
